hyaml/__init__.py
hyaml/__main__.py
hyaml/compiler.py
hyaml/translator.py
hyaml/grammar/HyamlLexer.py
hyaml/grammar/HyamlListener.py
hyaml/grammar/HyamlParser.py
hyaml/grammar/__init__.py
hyaml/methods/__init__.py
hyaml/methods/assignment.py
hyaml/methods/network.py
hyaml/methods/units.py
hyaml/methods/prelude/__init__.py
hyaml/methods/prelude/array.py
hyaml/methods/prelude/dictionary.py
hyaml/methods/prelude/number.py
hyaml/methods/prelude/polymorphic.py
hyaml/methods/prelude/runtime.py
hyaml/methods/prelude/string.py
hyaml-0.1.6.dist-info/LICENSE
hyaml-0.1.6.dist-info/METADATA
hyaml-0.1.6.dist-info/WHEEL
hyaml-0.1.6.dist-info/entry_points.txt
hyaml-0.1.6.dist-info/top_level.txt
hyaml-0.1.6.dist-info/RECORD
