Metadata-Version: 2.1
Name: hyaml
Version: 0.1.6
Summary: HYAML is a one-liner oriented language
Home-page: https://github.com/latera/hyaml
Author: Hydra Billing Solutions
License: UNKNOWN
Project-URL: Bug Reports, https://github.com/latera/hyaml/issues
Project-URL: Source, https://github.com/latera/hyaml
Keywords: antlr language one-liner hydra hyaml
Platform: UNKNOWN
Classifier: Development Status :: 4 - Beta
Classifier: Intended Audience :: Developers
Classifier: Framework :: Pytest
Classifier: Topic :: Software Development
Classifier: Topic :: Software Development :: Code Generators
Classifier: License :: OSI Approved :: Apache Software License
Classifier: Programming Language :: Python :: 3 :: Only
Classifier: Programming Language :: Python :: 3.7
Requires-Dist: antlr4-python3-runtime (>=4.7.1)
Provides-Extra: dev
Requires-Dist: black ; extra == 'dev'
Requires-Dist: unittest-xml-reporting ; extra == 'dev'
Requires-Dist: coverage ; extra == 'dev'
